create_neo4j_python_app/__init__.py
create_neo4j_python_app/_version.py
create_neo4j_python_app/create_app.py
create_neo4j_python_app-0.1.0.dist-info/LICENSE
create_neo4j_python_app-0.1.0.dist-info/METADATA
create_neo4j_python_app-0.1.0.dist-info/WHEEL
create_neo4j_python_app-0.1.0.dist-info/entry_points.txt
create_neo4j_python_app-0.1.0.dist-info/top_level.txt
create_neo4j_python_app-0.1.0.dist-info/RECORD
