Metadata-Version: 2.2
Name: create-neo4j-python-app
Version: 0.1.0
Summary: A Python API for Neo4j scaffolding tool
Author-email: Marius Conjeaud <marius.conjeaud@outlook.com>
License: MIT
Keywords: graph,neo4j,OGM,FastAPI
License-File: LICENSE
Requires-Dist: requests
Requires-Dist: inflect
Provides-Extra: dev
Requires-Dist: pytest; extra == "dev"
Requires-Dist: pytest-cov; extra == "dev"
Requires-Dist: pytest-mock; extra == "dev"
Requires-Dist: requests-mock; extra == "dev"
Requires-Dist: pre-commit; extra == "dev"
Requires-Dist: black; extra == "dev"
Requires-Dist: isort; extra == "dev"
Requires-Dist: mypy; extra == "dev"
Requires-Dist: types-requests; extra == "dev"
